antifp2/MERCI/MERCI_motif_locator.pl
antifp2/MERCI/antifp2_nagative.fasta
antifp2/MERCI/antifp2_positive.fasta
antifp2/MERCI/antifp2_positive_k8_fp10_KR
antifp2/MERCI/antifp2_positive_k8_fp10_KR.occurrences
antifp2/blast_db/antifp2.pdb
antifp2/blast_db/antifp2.phr
antifp2/blast_db/antifp2.pin
antifp2/blast_db/antifp2.pjs
antifp2/blast_db/antifp2.pot
antifp2/blast_db/antifp2.psq
antifp2/blast_db/antifp2.ptf
antifp2/blast_db/antifp2.pto
antifp2/blast_db/macos/blastp
antifp2/blast_db/ubuntu/blastp
antifp2/blast_db/windows/blastp.exe
antifp2/python_scripts/__init__.py
antifp2/python_scripts/antifp2.py
antifp2/python_scripts/antifp2_esm2.py
antifp2/python_scripts/antifp2_esm2_hybrid.py
antifp2/python_scripts/antifp2_ml_hybrid.py
antifp2/python_scripts/antifp2_xgboost_PAAC.pkl
antifp2/python_scripts/envfile
antifp2-1.1.0.dist-info/licenses/LICENSE.txt
antifp2-1.1.0.dist-info/METADATA
antifp2-1.1.0.dist-info/WHEEL
antifp2-1.1.0.dist-info/entry_points.txt
antifp2-1.1.0.dist-info/top_level.txt
antifp2-1.1.0.dist-info/RECORD
