Metadata-Version: 2.4
Name: antifp2
Version: 1.1.0
Summary: AntiFP2: A tool for prediction of Antifungal Proteins
Home-page: https://github.com/patrik-ackerman/antifp2/
Author: Pratik Shinde
Author-email: pratiks@iiitd.ac.in
Requires-Python: >=3.12
License-File: LICENSE.txt
Requires-Dist: fair-esm
Requires-Dist: huggingface-hub
Requires-Dist: pandas
Requires-Dist: torch
Requires-Dist: biopython
Requires-Dist: xgboost==3.0.4
Requires-Dist: pfeature
Requires-Dist: joblib
Dynamic: author
Dynamic: author-email
Dynamic: description
Dynamic: description-content-type
Dynamic: home-page
Dynamic: license-file
Dynamic: requires-dist
Dynamic: requires-python
Dynamic: summary
